setup.py
shmock/__init__.py
shmock/shell_command_mock.py
shmock.egg-info/PKG-INFO
shmock.egg-info/SOURCES.txt
shmock.egg-info/dependency_links.txt
shmock.egg-info/entry_points.txt
shmock.egg-info/requires.txt
shmock.egg-info/top_level.txt
shmock.egg-info/zip-safe