Metadata-Version: 1.1
Name: shmock
Version: 1.0.1
Summary: SHell command MOCKer for integration testing
Home-page: https://github.com/ImmobilienScout24/shmock
Author: Stefan Nordhausen
Author-email: stefan.nordhausen@immobilienscout24.de
License: Apache License 2.0
Platform: UNKNOWN
Classifier: Programming Language :: Python
Classifier: Programming Language :: Python :: 2
Classifier: Programming Language :: Python :: 2.6
Classifier: Programming Language :: Python :: 2.7
Classifier: Programming Language :: Python :: 3
